{
  "code": "thyroid",
  "lecture_label": "05-12 갑상선암 바이오마커 (임동석)",
  "essence": "갑상선암 림프절 전이 진단의 표준(FNAC + washout Tg)이 가진 한계를 'washout CYFRA 21-1'이라는 암 특이 보조마커로 메우는 이야기. 핵심은 'Tg는 갑상선 조직 마커 → CYFRA는 암 마커'라는 대비다.",
  "analogy": "Tg는 '갑상선이라는 동네 주민등록증'(정상 조직도 갖고 있어 헷갈림), CYFRA 21-1은 '암세포가 죽으며 흘린 지문'(암에서만 나와 범인 특정에 강함). 표준검사가 헷갈릴 때 지문으로 범인을 확정한다.",
  "concepts": [
    {
      "heading": "CYFRA 21-1 생성 기전: CK19 → Caspase-3 절단 → 가용성 단편",
      "points": [
        "CK19 = 40 kDa 산성 단백질, 상피세포 세포골격 → 분화 갑상선암(특히 유두암)에서 고발현",
        "암세포 아포토시스 중 Caspase-3가 CK19를 절단 → 가용성 단편 = CYFRA 21-1 방출 (anti-CYFRA 항체로 검출)",
        "수치 상승 = 단순 종양 부피 ❌ → CK19 발현↑ + 활성 아포토시스 동시 반영",
        "Dohmoto 2001(폐암 세포주): CK19 mRNA·Caspase-3·CYFRA 방출량 = 양의 상관 / Caspase-3 억제제(Z-DEVD-FMK) → CYFRA 방출 '감소'(인과 증명). Caspase-3는 필수 양성 인자"
      ]
    },
    {
      "heading": "Washout Tg vs Washout CYFRA 21-1 (핵심 대조)",
      "points": [
        "Tg = 갑상선 lineage 마커(정상 조직도 분비) → 수술 전/후 컷오프 크게 변동",
        "CYFRA = 암 특이 마커 → 정상 조직·TgAb 영향 없음 → universal cutoff(~1.12)",
        "분포: Tg는 양성/전이 겹침 큼, CYFRA는 겹침 거의 없음"
      ],
      "table": {
        "title": "Tg vs CYFRA 21-1 (2019 pilot / 컷오프)",
        "columns": ["항목", "Washout Tg", "Washout CYFRA 21-1"],
        "rows": [
          ["단독 민감도", "92.9%", "92.9%"],
          ["단독 특이도", "83.0%", "97.7%"],
          ["단독 정확도", "86.2%", "96.2%"],
          ["수술전 컷오프", "약 21.69 ng/mL", "약 0.85 ng/mL"],
          ["수술후 컷오프", "약 8.0 ng/mL", "약 0.98 ng/mL"],
          ["컷오프 변동", "크다(정상조직 간섭)", "거의 일정(universal)"]
        ]
      }
    },
    {
      "heading": "Washout Tg의 3대 한계 → CYFRA로 구제(discordance rescue)",
      "points": [
        "① 컷오프 편차: assay 민감도 0.1~3, 제시 컷오프 0.2~50 ng/mL → 표준화 곤란",
        "② 정상 갑상선 조직 간섭 → 위양성(수술 전·잔존조직)",
        "③ TgAb(~10~15% 환자) → Tg 수치 낮춰 위음성",
        "결과: FNAC+wTg ~9% 불일치, 13.9%(36/259) 불필요 neck dissection",
        "rescue: 불일치 22개(16.9%) 중 90.9%(20/22)를 CYFRA로 정확진단 / 동일 검체 추가측정(추가 천자 불필요) / 수술 상태 무관"
      ]
    },
    {
      "heading": "선정 근거·연구 메시지",
      "points": [
        "이상적 마커 3조건: cancer marker(조직 마커 ❌) / Tg처럼 측정 쉬움 / 다른 암에서 발현 낮음",
        "Dinets 2015 cystic PTC proteomics: 4개 상향(CK19·S100A13·ANXA3·CMBL). S100A13은 민감도 94% but 특이도 35% → 탈락. CK19(CYFRA)가 82/82로 가장 균형",
        "유방암 액와 LN·NSCLC 흉수에서 CYFRA 유용성 선행 입증 → 갑상선 적용 근거",
        "Take-home: unmet need에서 출발 / fancy omics보다 known marker 재적용 / production→removal 분자특성 / 예비논문 1편으론 부족=validation 필수"
      ]
    }
  ],
  "traps": [
    {
      "qref": "thyroid-1",
      "topic": "Caspase-3 억제제 효과",
      "correct": "✅ Caspase-3 억제제(Z-DEVD-FMK) 처리 시 CYFRA 21-1 방출은 '감소'한다. Caspase-3는 CK19를 잘라 CYFRA를 만드는 필수 양성 인자(인과 증명).",
      "trap": "❌ Caspase-3 억제제를 처리하면 CYFRA 방출이 '오히려 증가'하며, Caspase-3가 생성을 억제하는 음성 조절자다."
    },
    {
      "qref": "thyroid-2",
      "topic": "wTg 수술 전/후 컷오프",
      "correct": "✅ 정상 조직이 남은 것은 '수술 전'(부분절제 후) → 위양성 줄이려 컷오프 '높게'(~21.69). 정상조직 제거된 '수술 후'는 컷오프 '낮게'(~8.0).",
      "trap": "❌ 정상 조직 간섭 때문에 wTg 컷오프를 '수술 후에 더 높게, 수술 전에 더 낮게' 설정한다(전/후 뒤바뀜)."
    },
    {
      "qref": "thyroid-3",
      "topic": "컷오프 변동의 주체",
      "correct": "✅ 정상 갑상선 조직에서 분비돼 수술 전후 컷오프가 크게 변동하는 것은 'Tg'. CYFRA는 암 특이적이라 컷오프(~1.12)가 거의 일정.",
      "trap": "❌ 'CYFRA가 정상 조직에서도 분비되어' 컷오프가 변동하고, Tg는 암 특이적이라 컷오프가 일정하다(두 마커 역할 뒤바뀜)."
    },
    {
      "qref": "thyroid-4",
      "topic": "S100A13 특이도",
      "correct": "✅ S100A13은 민감도 ~94%지만 특이도 ~35%로 낮아 임상 적용 불가. 82/82로 균형 잡힌 CYFRA(CK19)가 최종 선정.",
      "trap": "❌ S100A13이 특이도 ~96%로 가장 균형 잡힌 마커로 최종 선정되었고, CYFRA(CK19)는 보조 후보에 그쳤다."
    },
    {
      "qref": "thyroid-g1",
      "topic": "Validation 필요성(take-home)",
      "correct": "✅ '예비 논문 1편으로는 부족, validation 과정도 중요'(2019 pilot reject → 2025 검증연구로 재현되어 확립).",
      "trap": "❌ 예비 논문 한 편으로 임상 유용성이 충분히 입증되어, 별도 검증 없이 곧바로 임상 도입 가능하다."
    },
    {
      "qref": "thyroid-g2",
      "topic": "Discordance rescue 방향",
      "correct": "✅ 구제는 양방향: Tg 위양성(benign 88중 15 오분류)을 CYFRA가 true negative로 정정(불필요 수술 회피) + FNAC가 놓친 전이 회수.",
      "trap": "❌ CYFRA의 구제는 거의 전적으로 위음성 림프절을 추가로 '찾아내는' 데에만(양성으로 정정) 기여한다."
    },
    {
      "qref": "thyroid-g3",
      "topic": "유방암 vs 갑상선암 마커 특이성·효용",
      "correct": "✅ CYFRA는 유방암 특이 마커가 아니라 상피종양 활성 반영(범용). washout 효용은 유방암 낮음(SLNB 등 확립), 갑상선암 높음(Tg가 lineage 특이→CYFRA 보완).",
      "trap": "❌ CYFRA는 유방암 특이 마커라 유방암 액와 LN에서 활용도 높고, 갑상선암에서는 비특이적이어서 보완 가치가 낮다."
    }
  ],
  "memorize": [
    "Tg=갑상선 조직 마커(정상도 분비, 컷오프 흔들림) / CYFRA=암 마커(universal ~1.12)",
    "CK19 →(Caspase-3 절단)→ CYFRA 21-1. 억제제 주면 CYFRA '감소'",
    "wTg 한계 3: 컷오프 편차·정상조직 위양성·TgAb 위음성 → 13.9% 불필요 수술",
    "불일치 22개 중 90.9%(20/22) CYFRA로 구제 / S100A13은 특이도 35%로 탈락"
  ],
  "figures": [
    {
      "pdf": "대학원발표_2026_갑상선암_biomarker (2).pdf",
      "page": 31,
      "caption": "CK19(40 kDa)와 CYFRA 21-1(CK19 유래 가용성 단편) 정의 — Caspase-3 절단 기전의 핵심 시각자료"
    },
    {
      "pdf": "대학원발표_2026_갑상선암_biomarker (2).pdf",
      "page": 49,
      "caption": "수술 상태별 Washout Tg vs CYFRA 21-1 컷오프 비교 — CYFRA의 universal line(~1.12) 안정성"
    }
  ]
}
